dalys/__init__.py
dalys/base_estimator.py
dalys/kernel_pca.py
dalys/lda.py
dalys/pca.py
dalys/tsne.py
dalys/umap_algo.py
dalys/utils/__init__.py
dalys/utils/utils.py
dalys-4.1.0.dist-info/METADATA
dalys-4.1.0.dist-info/WHEEL
dalys-4.1.0.dist-info/top_level.txt
dalys-4.1.0.dist-info/RECORD
