Metadata-Version: 2.1
Name: dalys
Version: 4.1.0
Summary: Dalys
Home-page: UNKNOWN
Author: Timofey Tkachenko
Author-email: tkachenko_t@protonmail.com
License: UNKNOWN
Project-URL: Source, https://github.com/yflexer/Dalys
Platform: UNKNOWN
